dropbox_paper_mcp/__init__.py
dropbox_paper_mcp/__main__.py
dropbox_paper_mcp/server.py
dropbox_paper_mcp-0.2.3.dist-info/METADATA
dropbox_paper_mcp-0.2.3.dist-info/WHEEL
dropbox_paper_mcp-0.2.3.dist-info/entry_points.txt
dropbox_paper_mcp-0.2.3.dist-info/RECORD
