Metadata-Version: 2.4
Name: dropbox-paper-mcp
Version: 0.2.3
Summary: Dropbox Paper MCP Server
Requires-Python: >=3.13
Requires-Dist: dropbox>=12.0.2
Requires-Dist: fastmcp>=2.14.3
Requires-Dist: python-dotenv>=1.2.1
